Javascript20NianFix1/README.md
Javascript20NianFix1/__init__.py
Javascript20NianFix1/__main__.py
Javascript20NianFix1/file.epub
Javascript20NianFix1/index.html
Javascript20NianFix1/css/__init__.py
Javascript20NianFix1/css/annotations.css
Javascript20NianFix1/css/main.css
Javascript20NianFix1/css/normalize.css
Javascript20NianFix1/css/popup.css
Javascript20NianFix1/font/__init__.py
Javascript20NianFix1/font/fontello.eot
Javascript20NianFix1/font/fontello.svg
Javascript20NianFix1/font/fontello.ttf
Javascript20NianFix1/font/fontello.woff
Javascript20NianFix1/img/__init__.py
Javascript20NianFix1/img/annotator-glyph-sprite.png
Javascript20NianFix1/img/annotator-icon-sprite.png
Javascript20NianFix1/img/apple-touch-icon.png
Javascript20NianFix1/img/cancelfullscreen.png
Javascript20NianFix1/img/close.png
Javascript20NianFix1/img/fullscreen.png
Javascript20NianFix1/img/loader.gif
Javascript20NianFix1/img/menu-icon.png
Javascript20NianFix1/img/save.png
Javascript20NianFix1/img/saved.png
Javascript20NianFix1/img/settings-s.png
Javascript20NianFix1/img/settings.png
Javascript20NianFix1/img/star.png
Javascript20NianFix1/js/__init__.py
Javascript20NianFix1/js/epub.js
Javascript20NianFix1/js/epub.min.js
Javascript20NianFix1/js/epub.min.map
Javascript20NianFix1/js/hooks.min.js
Javascript20NianFix1/js/hooks.min.map
Javascript20NianFix1/js/reader.js
Javascript20NianFix1/js/reader.js.map
Javascript20NianFix1/js/reader.min.js
Javascript20NianFix1/js/reader.min.map
Javascript20NianFix1/js/hooks/__init__.py
Javascript20NianFix1/js/hooks/extensions/__init__.py
Javascript20NianFix1/js/hooks/extensions/highlight.js
Javascript20NianFix1/js/libs/__init__.py
Javascript20NianFix1/js/libs/jquery.min.js
Javascript20NianFix1/js/libs/localforage.min.js
Javascript20NianFix1/js/libs/screenfull.js
Javascript20NianFix1/js/libs/screenfull.min.js
Javascript20NianFix1/js/libs/zip.min.js
Javascript20NianFix1/js/plugins/__init__.py
Javascript20NianFix1/js/plugins/hypothesis.js
javascript_20_nian_fix1-2025.3.24.1.dist-info/METADATA
javascript_20_nian_fix1-2025.3.24.1.dist-info/WHEEL
javascript_20_nian_fix1-2025.3.24.1.dist-info/entry_points.txt
javascript_20_nian_fix1-2025.3.24.1.dist-info/top_level.txt
javascript_20_nian_fix1-2025.3.24.1.dist-info/RECORD
